{"translation":{"id":"fra_lsg","name":"Louis Segond 1910","website":"https://ebible.org/Scriptures/details.php?id=fraLSG","licenseUrl":"https://ebible.org/Scriptures/details.php?id=fraLSG","licenseNotes":null,"shortName":"LSG","englishName":"French Louis Segond 1910 Bible","language":"fra","textDirection":"ltr","sha256":"511c6bdbe3244cdc9f86b3d119bf7b1a1aa101fa70dc70395ff662b528ce2c39","availableFormats":["json"],"listOfBooksApiLink":"/api/fra_lsg/books.json","numberOfBooks":66,"totalNumberOfChapters":1189,"totalNumberOfVerses":31170,"languageName":"français","languageEnglishName":"French"},"book":{"id":"JER","translationId":"fra_lsg","name":"JÉRÉMIE","commonName":"JÉRÉMIE","title":"JÉRÉMIE","order":24,"numberOfChapters":52,"sha256":"1abdc8cad8a3fd9caf00d935f5e3122b1dbb8423b9937cd1a619c830b03323c1","firstChapterNumber":1,"firstChapterApiLink":"/api/fra_lsg/JER/1.json","lastChapterNumber":52,"lastChapterApiLink":"/api/fra_lsg/JER/52.json","totalNumberOfVerses":1364},"chapter":{"number":33,"content":[{"type":"heading","content":["Promesses de rédemption"]},{"type":"verse","number":1,"content":["La parole de l’Éternel fut adressée à Jérémie une seconde fois, en ces mots, pendant qu’il était encore enfermé dans la cour de la prison:"]},{"type":"verse","number":2,"content":[{"text":"Ainsi parle l’Éternel, qui fait ces choses,","poem":1},{"lineBreak":true},{"text":"L’Éternel, qui les conçoit et les exécute,","poem":1},{"lineBreak":true},{"text":"Lui, dont le nom est l’Éternel:","poem":1}]},{"type":"verse","number":3,"content":[{"lineBreak":true},{"text":"Invoque-moi, et je te répondrai;","poem":1},{"lineBreak":true},{"text":"Je t’annoncerai de grandes choses, des choses cachées,","poem":1},{"lineBreak":true},{"text":"Que tu ne connais pas.","poem":1}]},{"type":"verse","number":4,"content":[{"lineBreak":true},{"text":"Car ainsi parle l’Éternel, le Dieu d’Israël,","poem":1},{"lineBreak":true},{"text":"Sur les maisons de cette ville","poem":1},{"lineBreak":true},{"text":"Et sur les maisons des rois de Juda,","poem":1},{"lineBreak":true},{"text":"Qui seront abattues par les terrasses et par l’épée,","poem":1}]},{"type":"verse","number":5,"content":[{"lineBreak":true},{"text":"Quand on s’avancera pour combattre les Chaldéens,","poem":1},{"lineBreak":true},{"text":"Et qu’elles seront remplies des cadavres des hommes","poem":1},{"lineBreak":true},{"text":"Que je frapperai dans ma colère et dans ma fureur,","poem":1},{"lineBreak":true},{"text":"Et à cause de la méchanceté desquels je cacherai ma face à cette ville;","poem":1}]},{"type":"verse","number":6,"content":[{"lineBreak":true},{"text":"Voici, je lui donnerai la guérison et la santé, je les guérirai,","poem":1},{"lineBreak":true},{"text":"Et je leur ouvrirai une source abondante de paix et de fidélité.","poem":1}]},{"type":"verse","number":7,"content":[{"lineBreak":true},{"text":"Je ramènerai les captifs de Juda et les captifs d’Israël,","poem":1},{"lineBreak":true},{"text":"Et je les rétablirai comme autrefois.","poem":1}]},{"type":"verse","number":8,"content":[{"lineBreak":true},{"text":"Je les purifierai de toutes les iniquités qu’ils ont commises contre moi,","poem":1},{"lineBreak":true},{"text":"Je leur pardonnerai toutes les iniquités par lesquelles ils m’ont offensé,","poem":1},{"lineBreak":true},{"text":"Par lesquelles ils se sont révoltés contre moi.","poem":1}]},{"type":"verse","number":9,"content":[{"lineBreak":true},{"text":"Cette ville sera pour moi un sujet de joie, de louange et de gloire,","poem":1},{"lineBreak":true},{"text":"Parmi toutes les nations de la terre,","poem":1},{"lineBreak":true},{"text":"Qui apprendront tout le bien que je leur ferai;","poem":1},{"lineBreak":true},{"text":"Elles seront étonnées et émues de tout le bonheur","poem":1},{"lineBreak":true},{"text":"Et de toute la prospérité que je leur accorderai.","poem":1}]},{"type":"verse","number":10,"content":[{"lineBreak":true},{"text":"Ainsi parle l’Éternel:","poem":1},{"lineBreak":true},{"text":"On entendra encore dans ce lieu","poem":1},{"lineBreak":true},{"text":"Dont vous dites: Il est désert, il n’y a plus d’hommes, plus de bêtes;","poem":1},{"lineBreak":true},{"text":"On entendra dans les villes de Juda et dans les rues de Jérusalem,","poem":1},{"lineBreak":true},{"text":"Dévastées, privées d’hommes, d’habitants, de bêtes,","poem":1}]},{"type":"verse","number":11,"content":[{"lineBreak":true},{"text":"Les cris de réjouissance et les cris d’allégresse,","poem":1},{"lineBreak":true},{"text":"Les chants du fiancé et les chants de la fiancée,","poem":1},{"lineBreak":true},{"text":"La voix de ceux qui disent:","poem":1},{"lineBreak":true},{"text":"Louez l’Éternel des armées,","poem":1},{"lineBreak":true},{"text":"Car l’Éternel est bon, car sa miséricorde dure à toujours!","poem":1},{"lineBreak":true},{"text":"La voix de ceux qui offrent des sacrifices d’actions de grâces","poem":1},{"lineBreak":true},{"text":"Dans la maison de l’Éternel.","poem":1},{"lineBreak":true},{"text":"Car je ramènerai les captifs du pays, je les rétablirai comme autrefois,","poem":1},{"lineBreak":true},{"text":"Dit l’Éternel.","poem":1}]},{"type":"verse","number":12,"content":[{"lineBreak":true},{"text":"Ainsi parle l’Éternel des armées:","poem":1},{"lineBreak":true},{"text":"Il y aura encore dans ce lieu","poem":1},{"lineBreak":true},{"text":"Qui est désert, sans hommes ni bêtes,","poem":1},{"lineBreak":true},{"text":"Et dans toutes ses villes,","poem":1},{"lineBreak":true},{"text":"Il y aura des demeures pour les bergers","poem":1},{"lineBreak":true},{"text":"Faisant reposer leurs troupeaux.","poem":1}]},{"type":"verse","number":13,"content":[{"lineBreak":true},{"text":"Dans les villes de la montagne, dans les villes de la plaine,","poem":1},{"lineBreak":true},{"text":"Dans les villes du midi,","poem":1},{"lineBreak":true},{"text":"Dans le pays de Benjamin et aux environs de Jérusalem,","poem":1},{"lineBreak":true},{"text":"Et dans les villes de Juda,","poem":1},{"lineBreak":true},{"text":"Les brebis passeront encore sous la main de celui qui les compte,","poem":1},{"lineBreak":true},{"text":"Dit l’Éternel.","poem":1}]},{"type":"verse","number":14,"content":[{"text":"Voici, les jours viennent, dit l’Éternel,","poem":1},{"lineBreak":true},{"text":"Où j’accomplirai la bonne parole","poem":1},{"lineBreak":true},{"text":"Que j’ai dite sur la maison d’Israël et sur la maison de Juda.","poem":1}]},{"type":"verse","number":15,"content":[{"lineBreak":true},{"text":"En ces jours et en ce temps-là,","poem":1},{"lineBreak":true},{"text":"Je ferai éclore à David un germe de justice;","poem":1},{"lineBreak":true},{"text":"Il pratiquera la justice et l’équité dans le pays.","poem":1}]},{"type":"verse","number":16,"content":[{"lineBreak":true},{"text":"En ces jours-là, Juda sera sauvé,","poem":1},{"lineBreak":true},{"text":"Jérusalem aura la sécurité dans sa demeure;","poem":1},{"lineBreak":true},{"text":"Et voici comment on l’appellera:","poem":1},{"lineBreak":true},{"text":"L’Éternel notre justice.","poem":1}]},{"type":"verse","number":17,"content":[{"lineBreak":true},{"text":"Car ainsi parle l’Éternel:","poem":1},{"lineBreak":true},{"text":"David ne manquera jamais d’un successeur","poem":1},{"lineBreak":true},{"text":"Assis sur le trône de la maison d’Israël;","poem":1}]},{"type":"verse","number":18,"content":[{"lineBreak":true},{"text":"Les sacrificateurs, les Lévites, ne manqueront jamais devant moi de successeurs","poem":1},{"lineBreak":true},{"text":"Pour offrir des holocaustes, brûler de l’encens avec les offrandes,","poem":1},{"lineBreak":true},{"text":"Et faire des sacrifices tous les jours.","poem":1}]},{"type":"verse","number":19,"content":[{"lineBreak":true},{"text":"La parole de l’Éternel fut adressée à Jérémie, en ces mots:","poem":1}]},{"type":"verse","number":20,"content":[{"lineBreak":true},{"text":"Ainsi parle l’Éternel:","poem":1},{"lineBreak":true},{"text":"Si vous pouvez rompre mon alliance avec le jour","poem":1},{"lineBreak":true},{"text":"Et mon alliance avec la nuit,","poem":1},{"lineBreak":true},{"text":"En sorte que le jour et la nuit ne soient plus en leur temps,","poem":1}]},{"type":"verse","number":21,"content":[{"lineBreak":true},{"text":"Alors aussi mon alliance sera rompue avec David, mon serviteur,","poem":1},{"lineBreak":true},{"text":"En sorte qu’il n’aura point de fils régnant sur son trône,","poem":1},{"lineBreak":true},{"text":"Et mon alliance avec les Lévites, les sacrificateurs, qui font mon service.","poem":1}]},{"type":"verse","number":22,"content":[{"lineBreak":true},{"text":"De même qu’on ne peut compter l’armée des cieux,","poem":1},{"lineBreak":true},{"text":"Ni mesurer le sable de la mer,","poem":1},{"lineBreak":true},{"text":"De même je multiplierai la postérité de David, mon serviteur,","poem":1},{"lineBreak":true},{"text":"Et les Lévites qui font mon service.","poem":1}]},{"type":"verse","number":23,"content":[{"text":"La parole de l’Éternel fut adressée à Jérémie, en ces mots:","poem":1}]},{"type":"verse","number":24,"content":[{"lineBreak":true},{"text":"N’as-tu pas remarqué ce que disent ces gens:","poem":1},{"lineBreak":true},{"text":"Les deux familles que l’Éternel avait choisies, il les a rejetées?","poem":1},{"lineBreak":true},{"text":"Ainsi ils méprisent mon peuple,","poem":1},{"lineBreak":true},{"text":"Au point de ne plus le regarder comme une nation.","poem":1}]},{"type":"verse","number":25,"content":[{"lineBreak":true},{"text":"Ainsi parle l’Éternel:","poem":1},{"lineBreak":true},{"text":"Si je n’ai pas fait mon alliance avec le jour et avec la nuit,","poem":1},{"lineBreak":true},{"text":"Si je n’ai pas établi les lois des cieux et de la terre,","poem":1}]},{"type":"verse","number":26,"content":[{"lineBreak":true},{"text":"Alors aussi je rejetterai la postérité de Jacob et de David, mon serviteur,","poem":1},{"lineBreak":true},{"text":"Et je ne prendrai plus dans sa postérité ceux qui domineront","poem":1},{"lineBreak":true},{"text":"Sur les descendants d’Abraham, d’Isaac et de Jacob.","poem":1},{"lineBreak":true},{"text":"Car je ramènerai leurs captifs, et j’aurai pitié d’eux.","poem":1}]}],"footnotes":[]},"thisChapterLink":"/api/fra_lsg/JER/33.json","thisChapterAudioLinks":{},"nextChapterApiLink":"/api/fra_lsg/JER/34.json","nextChapterAudioLinks":{},"previousChapterApiLink":"/api/fra_lsg/JER/32.json","previousChapterAudioLinks":{},"numberOfVerses":26}