{"translation":{"id":"fra_lsg","name":"Louis Segond 1910","website":"https://ebible.org/Scriptures/details.php?id=fraLSG","licenseUrl":"https://ebible.org/Scriptures/details.php?id=fraLSG","licenseNotes":null,"shortName":"LSG","englishName":"French Louis Segond 1910 Bible","language":"fra","textDirection":"ltr","sha256":"511c6bdbe3244cdc9f86b3d119bf7b1a1aa101fa70dc70395ff662b528ce2c39","availableFormats":["json"],"listOfBooksApiLink":"/api/fra_lsg/books.json","numberOfBooks":66,"totalNumberOfChapters":1189,"totalNumberOfVerses":31170,"languageName":"français","languageEnglishName":"French"},"book":{"id":"JOB","translationId":"fra_lsg","name":"JOB","commonName":"JOB","title":"JOB","order":18,"numberOfChapters":42,"sha256":"58bda4af63a3b67c2daf6de865ed0b0dfa785647b0b355279c796cfe5eb8186c","firstChapterNumber":1,"firstChapterApiLink":"/api/fra_lsg/JOB/1.json","lastChapterNumber":42,"lastChapterApiLink":"/api/fra_lsg/JOB/42.json","totalNumberOfVerses":1069},"chapter":{"number":18,"content":[{"type":"heading","content":["Second discours de Bildad à Job"]},{"type":"verse","number":1,"content":["Bildad de Schuach prit la parole et dit:"]},{"type":"verse","number":2,"content":[{"text":"Quand mettrez-vous un terme à ces discours?","poem":1},{"lineBreak":true},{"text":"Ayez de l’intelligence, puis nous parlerons.","poem":1}]},{"type":"verse","number":3,"content":[{"lineBreak":true},{"text":"Pourquoi sommes-nous regardés comme des bêtes?","poem":1},{"lineBreak":true},{"text":"Pourquoi ne sommes-nous à vos yeux que des brutes?","poem":1}]},{"type":"verse","number":4,"content":[{"lineBreak":true},{"text":"O toi qui te déchires dans ta fureur,","poem":1},{"lineBreak":true},{"text":"Faut-il, à cause de toi, que la terre devienne déserte?","poem":1},{"lineBreak":true},{"text":"Faut-il que les rochers disparaissent de leur place?","poem":1}]},{"type":"verse","number":5,"content":[{"lineBreak":true},{"text":"La lumière du méchant s’éteindra,","poem":1},{"lineBreak":true},{"text":"Et la flamme qui en jaillit cessera de briller.","poem":1}]},{"type":"verse","number":6,"content":[{"lineBreak":true},{"text":"La lumière s’obscurcira sous sa tente,","poem":1},{"lineBreak":true},{"text":"Et sa lampe au-dessus de lui s’éteindra.","poem":1}]},{"type":"verse","number":7,"content":[{"lineBreak":true},{"text":"Ses pas assurés seront à l’étroit;","poem":1},{"lineBreak":true},{"text":"Malgré ses efforts, il tombera.","poem":1}]},{"type":"verse","number":8,"content":[{"lineBreak":true},{"text":"Car il met les pieds sur un filet,","poem":1},{"lineBreak":true},{"text":"Il marche dans les mailles,","poem":1}]},{"type":"verse","number":9,"content":[{"lineBreak":true},{"text":"Il est saisi au piège par le talon,","poem":1},{"lineBreak":true},{"text":"Et le filet s’empare de lui;","poem":1}]},{"type":"verse","number":10,"content":[{"lineBreak":true},{"text":"Le cordeau est caché dans la terre,","poem":1},{"lineBreak":true},{"text":"Et la trappe est sur son sentier.","poem":1}]},{"type":"verse","number":11,"content":[{"lineBreak":true},{"text":"Des terreurs l’assiègent, l’entourent,","poem":1},{"lineBreak":true},{"text":"Le poursuivent par derrière.","poem":1}]},{"type":"verse","number":12,"content":[{"lineBreak":true},{"text":"La faim consume ses forces,","poem":1},{"lineBreak":true},{"text":"La misère est à ses côtés.","poem":1}]},{"type":"verse","number":13,"content":[{"lineBreak":true},{"text":"Les parties de sa peau sont l’une après l’autre dévorées,","poem":1},{"lineBreak":true},{"text":"Ses membres sont dévorés par le premier-né de la mort.","poem":1}]},{"type":"verse","number":14,"content":[{"lineBreak":true},{"text":"Il est arraché de sa tente où il se croyait en sûreté,","poem":1},{"lineBreak":true},{"text":"Il se traîne vers le roi des épouvantements.","poem":1}]},{"type":"verse","number":15,"content":[{"lineBreak":true},{"text":"Nul des siens n’habite sa tente,","poem":1},{"lineBreak":true},{"text":"Le soufre est répandu sur sa demeure.","poem":1}]},{"type":"verse","number":16,"content":[{"lineBreak":true},{"text":"En bas, ses racines se dessèchent;","poem":1},{"lineBreak":true},{"text":"En haut, ses branches sont coupées.","poem":1}]},{"type":"verse","number":17,"content":[{"lineBreak":true},{"text":"Sa mémoire disparaît de la terre,","poem":1},{"lineBreak":true},{"text":"Son nom n’est plus sur la face des champs.","poem":1}]},{"type":"verse","number":18,"content":[{"lineBreak":true},{"text":"Il est poussé de la lumière dans les ténèbres,","poem":1},{"lineBreak":true},{"text":"Il est chassé du monde.","poem":1}]},{"type":"verse","number":19,"content":[{"lineBreak":true},{"text":"Il ne laisse ni descendants ni postérité parmi son peuple,","poem":1},{"lineBreak":true},{"text":"Ni survivant dans les lieux qu’il habitait.","poem":1}]},{"type":"verse","number":20,"content":[{"lineBreak":true},{"text":"Les générations à venir seront étonnées de sa ruine,","poem":1},{"lineBreak":true},{"text":"Et la génération présente sera saisie d’effroi.","poem":1}]},{"type":"verse","number":21,"content":[{"lineBreak":true},{"text":"Point d’autre destinée pour le méchant,","poem":1},{"lineBreak":true},{"text":"Point d’autre sort pour qui ne connaît pas Dieu!","poem":1}]}],"footnotes":[]},"thisChapterLink":"/api/fra_lsg/JOB/18.json","thisChapterAudioLinks":{},"nextChapterApiLink":"/api/fra_lsg/JOB/19.json","nextChapterAudioLinks":{},"previousChapterApiLink":"/api/fra_lsg/JOB/17.json","previousChapterAudioLinks":{},"numberOfVerses":21}