{"translation":{"id":"fra_lsg","name":"Louis Segond 1910","website":"https://ebible.org/Scriptures/details.php?id=fraLSG","licenseUrl":"https://ebible.org/Scriptures/details.php?id=fraLSG","licenseNotes":null,"shortName":"LSG","englishName":"French Louis Segond 1910 Bible","language":"fra","textDirection":"ltr","sha256":"511c6bdbe3244cdc9f86b3d119bf7b1a1aa101fa70dc70395ff662b528ce2c39","availableFormats":["json"],"listOfBooksApiLink":"/api/fra_lsg/books.json","numberOfBooks":66,"totalNumberOfChapters":1189,"totalNumberOfVerses":31170,"languageName":"français","languageEnglishName":"French"},"book":{"id":"LAM","translationId":"fra_lsg","name":"LAMENTATIONS","commonName":"LAMENTATIONS","title":"LES LAMENTATIONS DE JÉRÉMIE","order":25,"numberOfChapters":5,"sha256":"f32f729ff20a0fc2a50103ee5568bc47ee23aab4202af07398af44b4a3695652","firstChapterNumber":1,"firstChapterApiLink":"/api/fra_lsg/LAM/1.json","lastChapterNumber":5,"lastChapterApiLink":"/api/fra_lsg/LAM/5.json","totalNumberOfVerses":154},"chapter":{"number":5,"content":[{"type":"heading","content":["Prière du peuple opprimé"]},{"type":"verse","number":1,"content":[{"text":"Souviens-toi, Éternel, de ce qui nous est arrivé!","poem":1},{"lineBreak":true},{"text":"Regarde, vois notre opprobre!","poem":1}]},{"type":"verse","number":2,"content":[{"lineBreak":true},{"text":"Notre héritage a passé à des étrangers,","poem":1},{"lineBreak":true},{"text":"Nos maisons à des inconnus.","poem":1}]},{"type":"verse","number":3,"content":[{"lineBreak":true},{"text":"Nous sommes orphelins, sans père;","poem":1},{"lineBreak":true},{"text":"Nos mères sont comme des veuves.","poem":1}]},{"type":"verse","number":4,"content":[{"lineBreak":true},{"text":"Nous buvons notre eau à prix d’argent,","poem":1},{"lineBreak":true},{"text":"Nous payons notre bois.","poem":1}]},{"type":"verse","number":5,"content":[{"lineBreak":true},{"text":"Nous sommes poursuivis, le joug sur le cou;","poem":1},{"lineBreak":true},{"text":"Nous sommes épuisés, nous n’avons point de repos.","poem":1}]},{"type":"verse","number":6,"content":[{"lineBreak":true},{"text":"Nous avons tendu la main vers l’Égypte, vers l’Assyrie,","poem":1},{"lineBreak":true},{"text":"Pour nous rassasier de pain.","poem":1}]},{"type":"verse","number":7,"content":[{"lineBreak":true},{"text":"Nos pères ont péché, ils ne sont plus,","poem":1},{"lineBreak":true},{"text":"Et c’est nous qui portons la peine de leurs iniquités.","poem":1}]},{"type":"verse","number":8,"content":[{"lineBreak":true},{"text":"Des esclaves dominent sur nous,","poem":1},{"lineBreak":true},{"text":"Et personne ne nous délivre de leurs mains.","poem":1}]},{"type":"verse","number":9,"content":[{"lineBreak":true},{"text":"Nous cherchons notre pain au péril de notre vie,","poem":1},{"lineBreak":true},{"text":"Devant l’épée du désert.","poem":1}]},{"type":"verse","number":10,"content":[{"lineBreak":true},{"text":"Notre peau est brûlante comme un four,","poem":1},{"lineBreak":true},{"text":"Par l’ardeur de la faim.","poem":1}]},{"type":"verse","number":11,"content":[{"lineBreak":true},{"text":"Ils ont déshonoré les femmes dans Sion,","poem":1},{"lineBreak":true},{"text":"Les vierges dans les villes de Juda.","poem":1}]},{"type":"verse","number":12,"content":[{"lineBreak":true},{"text":"Des chefs ont été pendus par leurs mains;","poem":1},{"lineBreak":true},{"text":"La personne des vieillards n’a pas été respectée.","poem":1}]},{"type":"verse","number":13,"content":[{"lineBreak":true},{"text":"Les jeunes hommes ont porté la meule,","poem":1},{"lineBreak":true},{"text":"Les enfants chancelaient sous des fardeaux de bois.","poem":1}]},{"type":"verse","number":14,"content":[{"lineBreak":true},{"text":"Les vieillards ne vont plus à la porte,","poem":1},{"lineBreak":true},{"text":"Les jeunes hommes ont cessé leurs chants.","poem":1}]},{"type":"verse","number":15,"content":[{"lineBreak":true},{"text":"La joie a disparu de nos cœurs,","poem":1},{"lineBreak":true},{"text":"Le deuil a remplacé nos danses.","poem":1}]},{"type":"verse","number":16,"content":[{"lineBreak":true},{"text":"La couronne de notre tête est tombée!","poem":1},{"lineBreak":true},{"text":"Malheur à nous, parce que nous avons péché!","poem":1}]},{"type":"verse","number":17,"content":[{"lineBreak":true},{"text":"Si notre cœur est souffrant,","poem":1},{"lineBreak":true},{"text":"Si nos yeux sont obscurcis,","poem":1}]},{"type":"verse","number":18,"content":[{"lineBreak":true},{"text":"C’est que la montagne de Sion est ravagée,","poem":1},{"lineBreak":true},{"text":"C’est que les renards s’y promènent.","poem":1}]},{"type":"verse","number":19,"content":[{"lineBreak":true},{"text":"Toi, l’Éternel, tu règnes à jamais;","poem":1},{"lineBreak":true},{"text":"Ton trône subsiste de génération en génération.","poem":1}]},{"type":"verse","number":20,"content":[{"lineBreak":true},{"text":"Pourquoi nous oublierais-tu pour toujours,","poem":1},{"lineBreak":true},{"text":"Nous abandonnerais-tu pour de longues années?","poem":1}]},{"type":"verse","number":21,"content":[{"lineBreak":true},{"text":"Fais-nous revenir vers toi, ô Éternel, et nous reviendrons!","poem":1},{"lineBreak":true},{"text":"Donne-nous encore des jours comme ceux d’autrefois!","poem":1}]},{"type":"verse","number":22,"content":[{"lineBreak":true},{"text":"Nous aurais-tu entièrement rejetés,","poem":1},{"lineBreak":true},{"text":"Et t’irriterais-tu contre nous jusqu’à l’excès?","poem":1}]}],"footnotes":[]},"thisChapterLink":"/api/fra_lsg/LAM/5.json","thisChapterAudioLinks":{},"nextChapterApiLink":"/api/fra_lsg/EZK/1.json","nextChapterAudioLinks":{},"previousChapterApiLink":"/api/fra_lsg/LAM/4.json","previousChapterAudioLinks":{},"numberOfVerses":22}