{"translation":{"id":"fra_lsg","name":"Louis Segond 1910","website":"https://ebible.org/Scriptures/details.php?id=fraLSG","licenseUrl":"https://ebible.org/Scriptures/details.php?id=fraLSG","licenseNotes":null,"shortName":"LSG","englishName":"French Louis Segond 1910 Bible","language":"fra","textDirection":"ltr","sha256":"511c6bdbe3244cdc9f86b3d119bf7b1a1aa101fa70dc70395ff662b528ce2c39","availableFormats":["json"],"listOfBooksApiLink":"/api/fra_lsg/books.json","numberOfBooks":66,"totalNumberOfChapters":1189,"totalNumberOfVerses":31170,"languageName":"français","languageEnglishName":"French"},"book":{"id":"ISA","translationId":"fra_lsg","name":"ÉSAÏE","commonName":"ÉSAÏE","title":"ÉSAÏE","order":23,"numberOfChapters":66,"sha256":"fefef2a2b6d21b8f8d301e4a725ab6d4d336d5ec2422e50e19c96291cacfb01c","firstChapterNumber":1,"firstChapterApiLink":"/api/fra_lsg/ISA/1.json","lastChapterNumber":66,"lastChapterApiLink":"/api/fra_lsg/ISA/66.json","totalNumberOfVerses":1291},"chapter":{"number":11,"content":[{"type":"heading","content":["Temps messianique"]},{"type":"verse","number":1,"content":[{"text":"Puis un rameau sortira du tronc d’Isaï,","poem":1},{"lineBreak":true},{"text":"Et un rejeton naîtra de ses racines.","poem":1}]},{"type":"verse","number":2,"content":[{"lineBreak":true},{"text":"L’Esprit de l’Éternel reposera sur lui:","poem":1},{"lineBreak":true},{"text":"Esprit de sagesse et d’intelligence,","poem":1},{"lineBreak":true},{"text":"Esprit de conseil et de force,","poem":1},{"lineBreak":true},{"text":"Esprit de connaissance et de crainte de l’Éternel.","poem":1}]},{"type":"verse","number":3,"content":[{"lineBreak":true},{"text":"Il respirera la crainte de l’Éternel;","poem":1},{"lineBreak":true},{"text":"Il ne jugera point sur l’apparence,","poem":1},{"lineBreak":true},{"text":"Il ne prononcera point sur un ouï-dire.","poem":1}]},{"type":"verse","number":4,"content":[{"lineBreak":true},{"text":"Mais il jugera les pauvres avec équité,","poem":1},{"lineBreak":true},{"text":"Et il prononcera avec droiture sur les malheureux de la terre;","poem":1},{"lineBreak":true},{"text":"Il frappera la terre de sa parole comme d’une verge,","poem":1},{"lineBreak":true},{"text":"Et du souffle de ses lèvres il fera mourir le méchant.","poem":1}]},{"type":"verse","number":5,"content":[{"lineBreak":true},{"text":"La justice sera la ceinture de ses flancs,","poem":1},{"lineBreak":true},{"text":"Et la fidélité la ceinture de ses reins.","poem":1}]},{"type":"verse","number":6,"content":[{"lineBreak":true},{"text":"Le loup habitera avec l’agneau,","poem":1},{"lineBreak":true},{"text":"Et la panthère se couchera avec le chevreau;","poem":1},{"lineBreak":true},{"text":"Le veau, le lionceau, et le bétail qu’on engraisse, seront ensemble,","poem":1},{"lineBreak":true},{"text":"Et un petit enfant les conduira.","poem":1}]},{"type":"verse","number":7,"content":[{"lineBreak":true},{"text":"La vache et l’ourse auront un même pâturage,","poem":1},{"lineBreak":true},{"text":"Leurs petits un même gîte;","poem":1},{"lineBreak":true},{"text":"Et le lion, comme le bœuf, mangera de la paille.","poem":1}]},{"type":"verse","number":8,"content":[{"lineBreak":true},{"text":"Le nourrisson s’ébattra sur l’antre de la vipère,","poem":1},{"lineBreak":true},{"text":"Et l’enfant sevré mettra sa main dans la caverne du basilic.","poem":1}]},{"type":"verse","number":9,"content":[{"lineBreak":true},{"text":"Il ne se fera ni tort ni dommage","poem":1},{"lineBreak":true},{"text":"Sur toute ma montagne sainte;","poem":1},{"lineBreak":true},{"text":"Car la terre sera remplie de la connaissance de l’Éternel,","poem":1},{"lineBreak":true},{"text":"Comme le fond de la mer par les eaux qui le couvrent.","poem":1}]},{"type":"verse","number":10,"content":[{"lineBreak":true},{"text":"En ce jour, le rejeton d’Isaï","poem":1},{"lineBreak":true},{"text":"Sera là comme une bannière pour les peuples;","poem":1},{"lineBreak":true},{"text":"Les nations se tourneront vers lui,","poem":1},{"lineBreak":true},{"text":"Et la gloire sera sa demeure.","poem":1}]},{"type":"verse","number":11,"content":[{"text":"Dans ce même temps, le Seigneur étendra une seconde fois sa main,","poem":1},{"lineBreak":true},{"text":"Pour racheter le reste de son peuple,","poem":1},{"lineBreak":true},{"text":"Dispersé en Assyrie et en Égypte,","poem":1},{"lineBreak":true},{"text":"A Pathros et en Éthiopie,","poem":1},{"lineBreak":true},{"text":"A Élam, à Schinear et à Hamath,","poem":1},{"lineBreak":true},{"text":"Et dans les îles de la mer.","poem":1}]},{"type":"verse","number":12,"content":[{"lineBreak":true},{"text":"Il élèvera une bannière pour les nations,","poem":1},{"lineBreak":true},{"text":"Il rassemblera les exilés d’Israël,","poem":1},{"lineBreak":true},{"text":"Et il recueillera les dispersés de Juda,","poem":1},{"lineBreak":true},{"text":"Des quatre extrémités de la terre.","poem":1}]},{"type":"verse","number":13,"content":[{"lineBreak":true},{"text":"La jalousie d’Éphraïm disparaîtra,","poem":1},{"lineBreak":true},{"text":"Et ses ennemis en Juda seront anéantis;","poem":1},{"lineBreak":true},{"text":"Éphraïm ne sera plus jaloux de Juda,","poem":1},{"lineBreak":true},{"text":"Et Juda ne sera plus hostile à Éphraïm.","poem":1}]},{"type":"verse","number":14,"content":[{"lineBreak":true},{"text":"Ils voleront sur l’épaule des Philistins à l’occident,","poem":1},{"lineBreak":true},{"text":"Ils pilleront ensemble les fils de l’Orient;","poem":1},{"lineBreak":true},{"text":"Édom et Moab seront la proie de leurs mains,","poem":1},{"lineBreak":true},{"text":"Et les fils d’Ammon leur seront assujettis.","poem":1}]},{"type":"verse","number":15,"content":[{"lineBreak":true},{"text":"L’Éternel desséchera la langue de la mer d’Égypte,","poem":1},{"lineBreak":true},{"text":"Et il lèvera sa main sur le fleuve, en soufflant avec violence:","poem":1},{"lineBreak":true},{"text":"Il le partagera en sept canaux,","poem":1},{"lineBreak":true},{"text":"Et on le traversera avec des souliers.","poem":1}]},{"type":"verse","number":16,"content":[{"lineBreak":true},{"text":"Et il y aura une route pour le reste de son peuple,","poem":1},{"lineBreak":true},{"text":"Qui sera échappé de l’Assyrie,","poem":1},{"lineBreak":true},{"text":"Comme il y en eut une pour Israël,","poem":1},{"lineBreak":true},{"text":"Le jour où il sortit du pays d’Égypte.","poem":1}]}],"footnotes":[]},"thisChapterLink":"/api/fra_lsg/ISA/11.json","thisChapterAudioLinks":{},"nextChapterApiLink":"/api/fra_lsg/ISA/12.json","nextChapterAudioLinks":{},"previousChapterApiLink":"/api/fra_lsg/ISA/10.json","previousChapterAudioLinks":{},"numberOfVerses":16}