{"translation":{"id":"fra_lsg","name":"Louis Segond 1910","website":"https://ebible.org/Scriptures/details.php?id=fraLSG","licenseUrl":"https://ebible.org/Scriptures/details.php?id=fraLSG","licenseNotes":null,"shortName":"LSG","englishName":"French Louis Segond 1910 Bible","language":"fra","textDirection":"ltr","sha256":"511c6bdbe3244cdc9f86b3d119bf7b1a1aa101fa70dc70395ff662b528ce2c39","availableFormats":["json"],"listOfBooksApiLink":"/api/fra_lsg/books.json","numberOfBooks":66,"totalNumberOfChapters":1189,"totalNumberOfVerses":31170,"languageName":"français","languageEnglishName":"French"},"book":{"id":"PRO","translationId":"fra_lsg","name":"PROVERBES","commonName":"PROVERBES","title":"LES PROVERBES","order":20,"numberOfChapters":31,"sha256":"335ecf15ba09752f1fd6fdce7575cd7803e62c1fb89fccb2e29e083160ce83ca","firstChapterNumber":1,"firstChapterApiLink":"/api/fra_lsg/PRO/1.json","lastChapterNumber":31,"lastChapterApiLink":"/api/fra_lsg/PRO/31.json","totalNumberOfVerses":915},"chapter":{"number":19,"content":[{"type":"verse","number":1,"content":[{"text":"Mieux vaut le pauvre qui marche dans son intégrité,","poem":1},{"lineBreak":true},{"text":"Que l’homme qui a des lèvres perverses et qui est un insensé.","poem":1}]},{"type":"verse","number":2,"content":[{"lineBreak":true},{"text":"Le manque de science n’est bon pour personne,","poem":1},{"lineBreak":true},{"text":"Et celui qui précipite ses pas tombe dans le péché.","poem":1}]},{"type":"verse","number":3,"content":[{"lineBreak":true},{"text":"La folie de l’homme pervertit sa voie,","poem":1},{"lineBreak":true},{"text":"Et c’est contre l’Éternel que son cœur s’irrite.","poem":1}]},{"type":"verse","number":4,"content":[{"lineBreak":true},{"text":"La richesse procure un grand nombre d’amis,","poem":1},{"lineBreak":true},{"text":"Mais le pauvre est séparé de son ami.","poem":1}]},{"type":"verse","number":5,"content":[{"lineBreak":true},{"text":"Le faux témoin ne restera pas impuni,","poem":1},{"lineBreak":true},{"text":"Et celui qui dit des mensonges n’échappera pas.","poem":1}]},{"type":"verse","number":6,"content":[{"lineBreak":true},{"text":"Beaucoup de gens flattent l’homme généreux,","poem":1},{"lineBreak":true},{"text":"Et tous sont les amis de celui qui fait des présents.","poem":1}]},{"type":"verse","number":7,"content":[{"lineBreak":true},{"text":"Tous les frères du pauvre le haïssent;","poem":1},{"lineBreak":true},{"text":"Combien plus ses amis s’éloignent-ils de lui!","poem":1},{"lineBreak":true},{"text":"Il leur adresse des paroles suppliantes, mais ils disparaissent.","poem":1}]},{"type":"verse","number":8,"content":[{"lineBreak":true},{"text":"Celui qui acquiert du sens aime son âme;","poem":1},{"lineBreak":true},{"text":"Celui qui garde l’intelligence trouve le bonheur.","poem":1}]},{"type":"verse","number":9,"content":[{"lineBreak":true},{"text":"Le faux témoin ne restera pas impuni,","poem":1},{"lineBreak":true},{"text":"Et celui qui dit des mensonges périra.","poem":1}]},{"type":"verse","number":10,"content":[{"lineBreak":true},{"text":"Il ne sied pas à un insensé de vivre dans les délices;","poem":1},{"lineBreak":true},{"text":"Combien moins à un esclave de dominer sur des princes!","poem":1}]},{"type":"verse","number":11,"content":[{"lineBreak":true},{"text":"L’homme qui a de la sagesse est lent à la colère,","poem":1},{"lineBreak":true},{"text":"Et il met sa gloire à oublier les offenses.","poem":1}]},{"type":"verse","number":12,"content":[{"lineBreak":true},{"text":"La colère du roi est comme le rugissement d’un lion,","poem":1},{"lineBreak":true},{"text":"Et sa faveur est comme la rosée sur l’herbe.","poem":1}]},{"type":"verse","number":13,"content":[{"lineBreak":true},{"text":"Un fils insensé est une calamité pour son père,","poem":1},{"lineBreak":true},{"text":"Et les querelles d’une femme sont une gouttière sans fin.","poem":1}]},{"type":"verse","number":14,"content":[{"lineBreak":true},{"text":"On peut hériter de ses pères une maison et des richesses,","poem":1},{"lineBreak":true},{"text":"Mais une femme intelligente est un don de l’Éternel.","poem":1}]},{"type":"verse","number":15,"content":[{"lineBreak":true},{"text":"La paresse fait tomber dans l’assoupissement,","poem":1},{"lineBreak":true},{"text":"Et l’âme nonchalante éprouve la faim.","poem":1}]},{"type":"verse","number":16,"content":[{"lineBreak":true},{"text":"Celui qui garde ce qui est commandé garde son âme;","poem":1},{"lineBreak":true},{"text":"Celui qui ne veille pas sur sa voie mourra.","poem":1}]},{"type":"verse","number":17,"content":[{"lineBreak":true},{"text":"Celui qui a pitié du pauvre prête à l’Éternel,","poem":1},{"lineBreak":true},{"text":"Qui lui rendra selon son œuvre.","poem":1}]},{"type":"verse","number":18,"content":[{"lineBreak":true},{"text":"Châtie ton fils, car il y a encore de l’espérance;","poem":1},{"lineBreak":true},{"text":"Mais ne désire point le faire mourir.","poem":1}]},{"type":"verse","number":19,"content":[{"lineBreak":true},{"text":"Celui que la colère emporte doit en subir la peine;","poem":1},{"lineBreak":true},{"text":"Car si tu le libères, tu devras y revenir.","poem":1}]},{"type":"verse","number":20,"content":[{"lineBreak":true},{"text":"Écoute les conseils, et reçois l’instruction,","poem":1},{"lineBreak":true},{"text":"Afin que tu sois sage dans la suite de ta vie.","poem":1}]},{"type":"verse","number":21,"content":[{"lineBreak":true},{"text":"Il y a dans le cœur de l’homme beaucoup de projets,","poem":1},{"lineBreak":true},{"text":"Mais c’est le dessein de l’Éternel qui s’accomplit.","poem":1}]},{"type":"verse","number":22,"content":[{"lineBreak":true},{"text":"Ce qui fait le charme d’un homme, c’est sa bonté;","poem":1},{"lineBreak":true},{"text":"Et mieux vaut un pauvre qu’un menteur.","poem":1}]},{"type":"verse","number":23,"content":[{"lineBreak":true},{"text":"La crainte de l’Éternel mène à la vie,","poem":1},{"lineBreak":true},{"text":"Et l’on passe la nuit rassasié, sans être visité par le malheur.","poem":1}]},{"type":"verse","number":24,"content":[{"lineBreak":true},{"text":"Le paresseux plonge sa main dans le plat,","poem":1},{"lineBreak":true},{"text":"Et il ne la ramène pas à sa bouche.","poem":1}]},{"type":"verse","number":25,"content":[{"lineBreak":true},{"text":"Frappe le moqueur, et le sot deviendra sage;","poem":1},{"lineBreak":true},{"text":"Reprends l’homme intelligent, et il comprendra la science.","poem":1}]},{"type":"verse","number":26,"content":[{"lineBreak":true},{"text":"Celui qui ruine son père et qui met en fuite sa mère","poem":1},{"lineBreak":true},{"text":"Est un fils qui fait honte et qui fait rougir.","poem":1}]},{"type":"verse","number":27,"content":[{"lineBreak":true},{"text":"Cesse, mon fils, d’écouter l’instruction,","poem":1},{"lineBreak":true},{"text":"Si c’est pour t’éloigner des paroles de la science.","poem":1}]},{"type":"verse","number":28,"content":[{"lineBreak":true},{"text":"Un témoin pervers se moque de la justice,","poem":1},{"lineBreak":true},{"text":"Et la bouche des méchants dévore l’iniquité.","poem":1}]},{"type":"verse","number":29,"content":[{"lineBreak":true},{"text":"Les châtiments sont prêts pour les moqueurs,","poem":1},{"lineBreak":true},{"text":"Et les coups pour le dos des insensés.","poem":1}]}],"footnotes":[]},"thisChapterLink":"/api/fra_lsg/PRO/19.json","thisChapterAudioLinks":{},"nextChapterApiLink":"/api/fra_lsg/PRO/20.json","nextChapterAudioLinks":{},"previousChapterApiLink":"/api/fra_lsg/PRO/18.json","previousChapterAudioLinks":{},"numberOfVerses":29}