{"translation":{"id":"fra_lsg","name":"Louis Segond 1910","website":"https://ebible.org/Scriptures/details.php?id=fraLSG","licenseUrl":"https://ebible.org/Scriptures/details.php?id=fraLSG","licenseNotes":null,"shortName":"LSG","englishName":"French Louis Segond 1910 Bible","language":"fra","textDirection":"ltr","sha256":"511c6bdbe3244cdc9f86b3d119bf7b1a1aa101fa70dc70395ff662b528ce2c39","availableFormats":["json"],"listOfBooksApiLink":"/api/fra_lsg/books.json","numberOfBooks":66,"totalNumberOfChapters":1189,"totalNumberOfVerses":31170,"languageName":"français","languageEnglishName":"French"},"book":{"id":"HOS","translationId":"fra_lsg","name":"OSÉE","commonName":"OSÉE","title":"OSÉE","order":28,"numberOfChapters":14,"sha256":"1f9a04d8b3bdff0445e0a9117e60f2f2a175e551d1e028338148be0a085c7426","firstChapterNumber":1,"firstChapterApiLink":"/api/fra_lsg/HOS/1.json","lastChapterNumber":14,"lastChapterApiLink":"/api/fra_lsg/HOS/14.json","totalNumberOfVerses":197},"chapter":{"number":9,"content":[{"type":"heading","content":["Déportation d’Israël"]},{"type":"verse","number":1,"content":[{"text":"Israël, ne te livre pas à la joie, à l’allégresse, comme les peuples,","poem":1},{"lineBreak":true},{"text":"De ce que tu t’es prostitué en abandonnant l’Éternel,","poem":1},{"lineBreak":true},{"text":"De ce que tu as aimé un salaire impur dans toutes les aires à blé!","poem":1}]},{"type":"verse","number":2,"content":[{"lineBreak":true},{"text":"L’aire et le pressoir ne les nourriront pas,","poem":1},{"lineBreak":true},{"text":"Et le moût leur fera défaut.","poem":1}]},{"type":"verse","number":3,"content":[{"lineBreak":true},{"text":"Ils ne resteront pas dans le pays de l’Éternel;","poem":1},{"lineBreak":true},{"text":"Éphraïm retournera en Égypte,","poem":1},{"lineBreak":true},{"text":"Et ils mangeront en Assyrie des aliments impurs.","poem":1}]},{"type":"verse","number":4,"content":[{"lineBreak":true},{"text":"Ils ne feront pas à l’Éternel des libations de vin:","poem":1},{"lineBreak":true},{"text":"Elles ne lui seraient point agréables.","poem":1},{"lineBreak":true},{"text":"Leurs sacrifices seront pour eux comme un pain de deuil;","poem":1},{"lineBreak":true},{"text":"Tous ceux qui en mangeront se rendront impurs;","poem":1},{"lineBreak":true},{"text":"Car leur pain ne sera que pour eux,","poem":1},{"lineBreak":true},{"text":"Il n’entrera point dans la maison de l’Éternel.","poem":1}]},{"type":"verse","number":5,"content":[{"lineBreak":true},{"text":"Que ferez-vous aux jours solennels,","poem":1},{"lineBreak":true},{"text":"Aux jours des fêtes de l’Éternel?","poem":1}]},{"type":"verse","number":6,"content":[{"lineBreak":true},{"text":"Car voici, ils partent à cause de la dévastation;","poem":1},{"lineBreak":true},{"text":"L’Égypte les recueillera,","poem":1},{"lineBreak":true},{"text":"Moph leur donnera des sépulcres;","poem":1},{"lineBreak":true},{"text":"Ce qu’ils ont de précieux, leur argent, sera la proie des ronces,","poem":1},{"lineBreak":true},{"text":"Et les épines croîtront dans leurs tentes.","poem":1}]},{"type":"verse","number":7,"content":[{"text":"Ils arrivent, les jours du châtiment,","poem":1},{"lineBreak":true},{"text":"Ils arrivent, les jours de la rétribution:","poem":1},{"lineBreak":true},{"text":"Israël va l’éprouver!","poem":1},{"lineBreak":true},{"text":"Le prophète est fou, l’homme inspiré a le délire,","poem":1},{"lineBreak":true},{"text":"A cause de la grandeur de tes iniquités et de tes rébellions.","poem":1}]},{"type":"verse","number":8,"content":[{"lineBreak":true},{"text":"Éphraïm est une sentinelle contre mon Dieu;","poem":1},{"lineBreak":true},{"text":"Le prophète… un filet d’oiseleur est sur toutes ses voies,","poem":1},{"lineBreak":true},{"text":"Un ennemi dans la maison de son Dieu.","poem":1}]},{"type":"verse","number":9,"content":[{"lineBreak":true},{"text":"Ils sont plongés dans la corruption, comme aux jours de Guibea;","poem":1},{"lineBreak":true},{"text":"L’Éternel se souviendra de leur iniquité,","poem":1},{"lineBreak":true},{"text":"Il punira leurs péchés.","poem":1}]},{"type":"verse","number":10,"content":[{"text":"J’ai trouvé Israël comme des raisins dans le désert,","poem":1},{"lineBreak":true},{"text":"J’ai vu vos pères comme les premiers fruits d’un figuier;","poem":1},{"lineBreak":true},{"text":"Mais ils sont allés vers Baal-Peor,","poem":1},{"lineBreak":true},{"text":"Ils se sont consacrés à l’infâme idole,","poem":1},{"lineBreak":true},{"text":"Et ils sont devenus abominables comme l’objet de leur amour.","poem":1}]},{"type":"verse","number":11,"content":[{"lineBreak":true},{"text":"La gloire d’Éphraïm s’envolera comme un oiseau:","poem":1},{"lineBreak":true},{"text":"Plus de naissance, plus de grossesse, plus de conception.","poem":1}]},{"type":"verse","number":12,"content":[{"lineBreak":true},{"text":"S’ils élèvent leurs enfants,","poem":1},{"lineBreak":true},{"text":"Je les en priverai avant qu’ils soient des hommes;","poem":1},{"lineBreak":true},{"text":"Et malheur à eux, quand je les abandonnerai!","poem":1}]},{"type":"verse","number":13,"content":[{"lineBreak":true},{"text":"Éphraïm, aussi loin que portent mes regards du côté de Tyr,","poem":1},{"lineBreak":true},{"text":"Est planté dans un lieu agréable;","poem":1},{"lineBreak":true},{"text":"Mais Éphraïm mènera ses enfants vers celui qui les tuera.","poem":1}]},{"type":"verse","number":14,"content":[{"lineBreak":true},{"text":"Donne-leur, ô Éternel!… Que leur donneras-tu?…","poem":1},{"lineBreak":true},{"text":"Donne-leur un sein qui avorte et des mamelles desséchées!","poem":1}]},{"type":"verse","number":15,"content":[{"lineBreak":true},{"text":"Toute leur méchanceté se montre à Guilgal;","poem":1},{"lineBreak":true},{"text":"C’est là que je les ai pris en aversion.","poem":1},{"lineBreak":true},{"text":"A cause de la malice de leurs œuvres,","poem":1},{"lineBreak":true},{"text":"Je les chasserai de ma maison.","poem":1},{"lineBreak":true},{"text":"Je ne les aimerai plus;","poem":1},{"lineBreak":true},{"text":"Tous leurs chefs sont des rebelles.","poem":1}]},{"type":"verse","number":16,"content":[{"lineBreak":true},{"text":"Éphraïm est frappé, sa racine est devenue sèche;","poem":1},{"lineBreak":true},{"text":"Ils ne porteront plus de fruit;","poem":1},{"lineBreak":true},{"text":"Et s’ils ont des enfants,","poem":1},{"lineBreak":true},{"text":"Je ferai périr les objets de leur tendresse.","poem":1}]},{"type":"verse","number":17,"content":[{"lineBreak":true},{"text":"Mon Dieu les rejettera, parce qu’ils ne l’ont pas écouté,","poem":1},{"lineBreak":true},{"text":"Et ils seront errants parmi les nations.","poem":1}]}],"footnotes":[]},"thisChapterLink":"/api/fra_lsg/HOS/9.json","thisChapterAudioLinks":{},"nextChapterApiLink":"/api/fra_lsg/HOS/10.json","nextChapterAudioLinks":{},"previousChapterApiLink":"/api/fra_lsg/HOS/8.json","previousChapterAudioLinks":{},"numberOfVerses":17}